swanki/__init__.py
swanki/__main__.py
swanki/__version__.py
swanki/clean_md.py
swanki/clean_transcript.py
swanki/combine.py
swanki/cut.py
swanki/extract_jpg_links.py
swanki/generate_cards.py
swanki/generate_image_cards.py
swanki/generate_transcript.py
swanki/image_add_back.py
swanki/image_reader.py
swanki/image_summary_insert.py
swanki/image_summary_replace.py
swanki/mathpix.py
swanki/recombine_md.py
swanki/split_pdf.py
swanki/token_count.py
swanki-1.0.2.dist-info/METADATA
swanki-1.0.2.dist-info/WHEEL
swanki-1.0.2.dist-info/entry_points.txt
swanki-1.0.2.dist-info/top_level.txt
swanki-1.0.2.dist-info/RECORD
