Metadata-Version: 2.1
Name: swanki
Version: 1.0.2
Summary: An example package
Author-email: Michael Volk <michaeljvolk7@gmail.com>
Project-URL: Homepage, https://github.com/Mjvolk3/Swanki
Keywords: An example package,starving artist
Classifier: License :: OSI Approved :: MIT License
Classifier: Programming Language :: Python
Classifier: Programming Language :: Python :: 3
Requires-Python: >=3.10
Requires-Dist: manim
Requires-Dist: python-dotenv
Requires-Dist: langchain-community
Requires-Dist: langchain
Requires-Dist: openai
Requires-Dist: tiktoken
Requires-Dist: PyPDF2
Requires-Dist: build
Requires-Dist: twine
Requires-Dist: python-semantic-release
Provides-Extra: dev
Requires-Dist: black; extra == "dev"
Requires-Dist: semantic-release; extra == "dev"
Requires-Dist: pip-tools; extra == "dev"
Requires-Dist: pytest; extra == "dev"
